TkToolsD/AtlasPacker.py
TkToolsD/Combobox.py
TkToolsD/CommonWidgets.py
TkToolsD/ConfigEditor.py
TkToolsD/DataTableView.py
TkToolsD/ImgView.py
TkToolsD/InfoProgressBar.py
TkToolsD/MultiFileChooser.py
TkToolsD/ScrollFrame.py
TkToolsD/TextScrollView.py
TkToolsD/VersionWidget.py
TkToolsD/__init__.py
TkToolsD/res/TkinterDnD2-0.3.tar.gz
TkToolsD/res/d_checked.png
TkToolsD/res/d_normal.png
TkToolsD/res/d_part.png
TkToolsD/res/f_checked.png
TkToolsD/res/f_normal.png
TkToolsD/res/tkdnd-2.9.2-linux-x64.tgz
TkToolsD/res/tkdnd-2.9.2-osx-x64.tgz
TkToolsD/res/tkdnd-2.9.2-windows-x64.tar.gz
TkToolsD/res/tkdnd-2.9.2-windows-x86.tar.gz
TkToolsD-0.2.7.dist-info/METADATA
TkToolsD-0.2.7.dist-info/WHEEL
TkToolsD-0.2.7.dist-info/top_level.txt
TkToolsD-0.2.7.dist-info/RECORD
